mpi_list/F.py
mpi_list/__init__.py
mpi_list/dfm.py
mpi_list/fill.py
mpi_list/gather.py
mpi_list/pscan.py
mpi_list/reducer.py
mpi_list/segment.py
mpi_list-0.3.dist-info/AUTHORS.rst
mpi_list-0.3.dist-info/LICENSE.txt
mpi_list-0.3.dist-info/METADATA
mpi_list-0.3.dist-info/WHEEL
mpi_list-0.3.dist-info/top_level.txt
mpi_list-0.3.dist-info/RECORD
