Metadata-Version: 2.1
Name: mpi-list
Version: 0.3
Summary: A Distributed List API over MPI
Home-page: https://github.com/frobnitzem/mpi_list/
Author: David M. Rogers
Author-email: predictivestatmech@gmail.com
License: MIT
Project-URL: Documentation, https://mpi-list.readthedocs.io/
Platform: any
Classifier: Development Status :: 4 - Beta
Classifier: Programming Language :: Python
Classifier: Topic :: Database
Requires-Python: >=3.6
Requires-Dist: numpy
Requires-Dist: mpi4py
Requires-Dist: importlib-metadata ; python_version < "3.8"
Provides-Extra: testing
Requires-Dist: setuptools ; extra == 'testing'
Requires-Dist: pytest ; extra == 'testing'
Requires-Dist: pytest-cov ; extra == 'testing'
